odoo/addons/ssi_appointment_request/README.rst
odoo/addons/ssi_appointment_request/__init__.py
odoo/addons/ssi_appointment_request/__manifest__.py
odoo/addons/ssi_appointment_request/data/approval_template_data.xml
odoo/addons/ssi_appointment_request/data/ir_sequence_data.xml
odoo/addons/ssi_appointment_request/data/policy_template_data.xml
odoo/addons/ssi_appointment_request/data/sequence_template_data.xml
odoo/addons/ssi_appointment_request/i18n/ssi_appointment_request.pot
odoo/addons/ssi_appointment_request/models/__init__.py
odoo/addons/ssi_appointment_request/models/appointment_request.py
odoo/addons/ssi_appointment_request/models/appointment_schedule.py
odoo/addons/ssi_appointment_request/models/appointment_type.py
odoo/addons/ssi_appointment_request/security/ir.model.access.csv
odoo/addons/ssi_appointment_request/security/ir_module_category_data.xml
odoo/addons/ssi_appointment_request/security/res_group_data.xml
odoo/addons/ssi_appointment_request/static/description/icon.png
odoo/addons/ssi_appointment_request/views/appointment_request_views.xml
odoo/addons/ssi_appointment_request/views/appointment_schedule_views.xml
odoo/addons/ssi_appointment_request/views/appointment_type_views.xml
odoo14_addon_ssi_appointment_request-14.0.1.5.0.dist-info/METADATA
odoo14_addon_ssi_appointment_request-14.0.1.5.0.dist-info/WHEEL
odoo14_addon_ssi_appointment_request-14.0.1.5.0.dist-info/top_level.txt
odoo14_addon_ssi_appointment_request-14.0.1.5.0.dist-info/RECORD
